{
    "_links": {
        "self": {
            "href": ""
        },
        "type": {
            "href": "http:\/\/drupal.org\/rest\/type\/paragraph\/html"
        }
    },
    "id": [
        {
            "value": 42
        }
    ],
    "uuid": [
        {
            "value": "3a988d69-87e4-4f11-b2e2-7505f96dc82c"
        }
    ],
    "revision_id": [
        {
            "value": 179
        }
    ],
    "langcode": [
        {
            "value": "en",
            "lang": "en"
        }
    ],
    "type": [
        {
            "target_id": "html"
        }
    ],
    "status": [
        {
            "value": true,
            "lang": "en"
        }
    ],
    "created": [
        {
            "value": "2019-09-26T06:08:20+00:00",
            "lang": "en",
            "format": "Y-m-d\\TH:i:sP"
        }
    ],
    "parent_id": [
        {
            "value": "12"
        }
    ],
    "parent_type": [
        {
            "value": "node"
        }
    ],
    "parent_field_name": [
        {
            "value": "field_paragraphs"
        }
    ],
    "behavior_settings": [
        {
            "value": []
        }
    ],
    "default_langcode": [
        {
            "value": true,
            "lang": "en"
        }
    ],
    "field_body": [
        {
            "value": "LOS ANGELES \u2013 Esta semana, la Agencia de Protecci\u00f3n Ambiental de los Estados Unidos (EPA, por sus siglas en ingl\u00e9s) trabajar\u00e1 con el Departamento de Reciclaje y Recuperaci\u00f3n de Recursos de California (CalRecycle) para identificar y eliminar los desechos s\u00f3lidos en el sitio del incendio Fruitland fuego del magnesio en Maywood, Calif.\r\n\r\n\r\nLos materiales que se encuentran en las instalaciones, los cuales incluyen desechos s\u00f3lidos y peligrosos, ser\u00e1n separados, categorizados y cargados en camiones para su transporte a instalaciones de eliminaci\u00f3n aprobadas. La EPA ha identificado metales como ars\u00e9nico, cadmio, cromo, plomo y mercurio como los contaminantes de preocupaci\u00f3n en el sitio. Los camiones de traslado no transitar\u00e1n por el vecindario de la calle E. 52nd St. La EPA tambi\u00e9n controlar\u00e1 la generaci\u00f3n y la migraci\u00f3n de polvo usando agua para mojar los materiales.\r\n\r\n\r\nEn preparaci\u00f3n para las actividades de eliminaci\u00f3n, la EPA ha completado lo siguiente:\r\n\r\n\r\n    Barrera de Escombros: se instal\u00f3 una barrera de escombros a lo largo del l\u00edmite sur entre la instalaci\u00f3n y la propiedad residencial adyacente para proteger contra el polvo, el ruido y los escombros;\r\n    Prevenci\u00f3n de la Contaminaci\u00f3n del Agua de Tormenta: se instalaron controles de erosi\u00f3n de paja alrededor del per\u00edmetro del sitio para evitar que la lluvia propagara la ceniza o tierra fuera del sitio;\r\n    Supresi\u00f3n de Polvo: un sellador de suelo, similar a un pegamento, fue aplicado a los escombros y suelos en el sitio para controlar la generaci\u00f3n de polvo.\r\n    Monitoreo del aire: se han establecido cinco estaciones temporales de monitoreo del aire alrededor del per\u00edmetro del sitio, tanto en la direcci\u00f3n del viento y en contra del viento, incluyendo dos en las propiedades residenciales directamente adyacentes al sitio. Estas estaciones de monitoreo del aire recoger\u00e1n muestras y medir\u00e1n el polvo total en el aire, y ser\u00e1n revisadas en tiempo real por los contratistas de la EPA. Adem\u00e1s, se har\u00e1 monitoreo del aire para compuestos org\u00e1nicos vol\u00e1tiles (COV, por sus siglas en ingl\u00e9s) en el sitio. Hasta la fecha, no se han detectado COV en el aire.\r\n\r\n\r\nUna vez que la eliminaci\u00f3n de residuos se haya completado, la EPA evaluar\u00e1 las condiciones del sitio para asegurar que no queden residuos peligrosos. La EPA no prev\u00e9 la necesidad de excavaci\u00f3n debajo de la superficie ya que la mayor parte de la superficie del suelo en el sitio estaba cubierta de hormig\u00f3n o asfalto antes del incendio.\r\n\r\n\r\nHistoria del Sitio\r\n\r\nEl 14 de junio de 2016, un incendio destruy\u00f3 una propiedad industrial ubicada en 3570 Fruitland Avenue en Maywood, California. El fuego afect\u00f3 a dos instalaciones en la propiedad Fruitland Avenue - Panda International Trading (PIT), una empresa de reciclaje de chatarra y SOKOR metals, un negocio de reciclaje de productos electr\u00f3nicos. La EPA continuar\u00e1 coordinando con las agencias estatales y locales, incluyendo el Departamento de Salud P\u00fablica del condado de los \u00c1ngeles, el Departamento de Bomberos del Condado de Los \u00c1ngeles - Divisi\u00f3n de Materiales Peligrosos (HHMD) Departamento del condado de Los \u00c1ngeles de Salud P\u00fablica, la Divisi\u00f3n de Materiales Peligrosos en el condado de Los \u00c1ngeles de incendio Salud y el Departamento de Reciclaje y Recuperaci\u00f3n de Recursos.\r\n\r\n\r\nPara obtener m\u00e1s informaci\u00f3n, por favor visite: https:\/\/www.epa.gov\/ca\/epa-response-fruitland-magnesium-fire-maywood-ca\r\n\r\n\r\n###\r\n\r\n\r\n",
            "format": "filtered_html",
            "processed": "<p>LOS ANGELES \u2013 Esta semana, la Agencia de Protecci\u00f3n Ambiental de los Estados Unidos (EPA, por sus siglas en ingl\u00e9s) trabajar\u00e1 con el Departamento de Reciclaje y Recuperaci\u00f3n de Recursos de California (CalRecycle) para identificar y eliminar los desechos s\u00f3lidos en el sitio del incendio Fruitland fuego del magnesio en Maywood, Calif.<\/p>\n<p>Los materiales que se encuentran en las instalaciones, los cuales incluyen desechos s\u00f3lidos y peligrosos, ser\u00e1n separados, categorizados y cargados en camiones para su transporte a instalaciones de eliminaci\u00f3n aprobadas. La EPA ha identificado metales como ars\u00e9nico, cadmio, cromo, plomo y mercurio como los contaminantes de preocupaci\u00f3n en el sitio. Los camiones de traslado no transitar\u00e1n por el vecindario de la calle E. 52nd St. La EPA tambi\u00e9n controlar\u00e1 la generaci\u00f3n y la migraci\u00f3n de polvo usando agua para mojar los materiales.<\/p>\n<p>En preparaci\u00f3n para las actividades de eliminaci\u00f3n, la EPA ha completado lo siguiente:<\/p>\n<p>    Barrera de Escombros: se instal\u00f3 una barrera de escombros a lo largo del l\u00edmite sur entre la instalaci\u00f3n y la propiedad residencial adyacente para proteger contra el polvo, el ruido y los escombros;<br \/>\n    Prevenci\u00f3n de la Contaminaci\u00f3n del Agua de Tormenta: se instalaron controles de erosi\u00f3n de paja alrededor del per\u00edmetro del sitio para evitar que la lluvia propagara la ceniza o tierra fuera del sitio;<br \/>\n    Supresi\u00f3n de Polvo: un sellador de suelo, similar a un pegamento, fue aplicado a los escombros y suelos en el sitio para controlar la generaci\u00f3n de polvo.<br \/>\n    Monitoreo del aire: se han establecido cinco estaciones temporales de monitoreo del aire alrededor del per\u00edmetro del sitio, tanto en la direcci\u00f3n del viento y en contra del viento, incluyendo dos en las propiedades residenciales directamente adyacentes al sitio. Estas estaciones de monitoreo del aire recoger\u00e1n muestras y medir\u00e1n el polvo total en el aire, y ser\u00e1n revisadas en tiempo real por los contratistas de la EPA. Adem\u00e1s, se har\u00e1 monitoreo del aire para compuestos org\u00e1nicos vol\u00e1tiles (COV, por sus siglas en ingl\u00e9s) en el sitio. Hasta la fecha, no se han detectado COV en el aire.<\/p>\n<p>Una vez que la eliminaci\u00f3n de residuos se haya completado, la EPA evaluar\u00e1 las condiciones del sitio para asegurar que no queden residuos peligrosos. La EPA no prev\u00e9 la necesidad de excavaci\u00f3n debajo de la superficie ya que la mayor parte de la superficie del suelo en el sitio estaba cubierta de hormig\u00f3n o asfalto antes del incendio.<\/p>\n<p>Historia del Sitio<\/p>\n<p>El 14 de junio de 2016, un incendio destruy\u00f3 una propiedad industrial ubicada en 3570 Fruitland Avenue en Maywood, California. El fuego afect\u00f3 a dos instalaciones en la propiedad Fruitland Avenue - Panda International Trading (PIT), una empresa de reciclaje de chatarra y SOKOR metals, un negocio de reciclaje de productos electr\u00f3nicos. La EPA continuar\u00e1 coordinando con las agencias estatales y locales, incluyendo el Departamento de Salud P\u00fablica del condado de los \u00c1ngeles, el Departamento de Bomberos del Condado de Los \u00c1ngeles - Divisi\u00f3n de Materiales Peligrosos (HHMD) Departamento del condado de Los \u00c1ngeles de Salud P\u00fablica, la Divisi\u00f3n de Materiales Peligrosos en el condado de Los \u00c1ngeles de incendio Salud y el Departamento de Reciclaje y Recuperaci\u00f3n de Recursos.<\/p>\n<p>Para obtener m\u00e1s informaci\u00f3n, por favor visite: <a href=\"https:\/\/www.epa.gov\/ca\/epa-response-fruitland-magnesium-fire-maywood-ca\">https:\/\/www.epa.gov\/ca\/epa-response-fruitland-magnesium-fire-maywood-ca<\/a><\/p>\n<p>###<\/p>\n"
        }
    ]
}
