{
    "_links": {
        "self": {
            "href": "http:\/\/default\/taxonomy\/term\/29?_format=hal_json"
        },
        "type": {
            "href": "http:\/\/drupal.org\/rest\/type\/taxonomy_term\/emergencies_and_cleanup_topics"
        },
        "http:\/\/drupal.org\/rest\/relation\/taxonomy_term\/emergencies_and_cleanup_topics\/parent": [
            {
                "href": "http:\/\/default\/taxonomy\/term\/28?_format=hal_json"
            }
        ]
    },
    "tid": [
        {
            "value": 29
        }
    ],
    "uuid": [
        {
            "value": "70de11b9-07d8-40b2-930c-9fb3d87f8614"
        }
    ],
    "revision_id": [
        {
            "value": 66
        }
    ],
    "langcode": [
        {
            "value": "en",
            "lang": "en"
        }
    ],
    "vid": [
        {
            "target_id": "emergencies_and_cleanup_topics"
        }
    ],
    "revision_created": [
        {
            "value": "2019-09-04T22:22:23+00:00",
            "format": "Y-m-d\\TH:i:sP"
        }
    ],
    "status": [
        {
            "value": true,
            "lang": "en"
        }
    ],
    "name": [
        {
            "value": "Emergency Management",
            "lang": "en"
        }
    ],
    "weight": [
        {
            "value": 0
        }
    ],
    "_embedded": {
        "http:\/\/drupal.org\/rest\/relation\/taxonomy_term\/emergencies_and_cleanup_topics\/parent": [
            {
                "_links": {
                    "self": {
                        "href": "http:\/\/default\/taxonomy\/term\/28?_format=hal_json"
                    },
                    "type": {
                        "href": "http:\/\/drupal.org\/rest\/type\/taxonomy_term\/emergencies_and_cleanup_topics"
                    }
                },
                "uuid": [
                    {
                        "value": "03c8fd5e-2bd5-48db-a914-986463dde504"
                    }
                ]
            }
        ]
    },
    "changed": [
        {
            "value": "2019-09-04T22:22:56+00:00",
            "lang": "en",
            "format": "Y-m-d\\TH:i:sP"
        }
    ],
    "default_langcode": [
        {
            "value": true,
            "lang": "en"
        }
    ],
    "revision_translation_affected": [
        {
            "value": true,
            "lang": "en"
        }
    ],
    "path": [
        {
            "alias": null,
            "pid": null,
            "langcode": "en",
            "lang": "en"
        }
    ]
}